orchestration/__init__.py
orchestration/citation.py
orchestration/completion_request_base.py
orchestration/completion_response.py
orchestration/knowledge_management_completion_request.py
orchestration/message_history_item.py
orchestration/orchestration_settings.py
foundationallm_models-0.7.0.dist-info/LICENSE
foundationallm_models-0.7.0.dist-info/METADATA
foundationallm_models-0.7.0.dist-info/WHEEL
foundationallm_models-0.7.0.dist-info/top_level.txt
foundationallm_models-0.7.0.dist-info/RECORD
