Metadata-Version: 2.1
Name: foundationallm-models
Version: 0.7.0
Summary: Enables integration with the FoundationaLLM data models.
Author-email: FoundationaLLM <dev@foundationallm.ai>
Project-URL: Homepage, https://foundationallm.ai
Project-URL: Issues, https://github.com/solliancenet/foundationallm/issues
Classifier: Programming Language :: Python :: 3
Classifier: License :: OSI Approved :: MIT License
Classifier: Operating System :: OS Independent
Requires-Python: >=3.11
License-File: LICENSE
